pharia_telemetry/__init__.py
pharia_telemetry/_version.py
pharia_telemetry/py.typed
pharia_telemetry/baggage/__init__.py
pharia_telemetry/baggage/processors.py
pharia_telemetry/baggage/propagation.py
pharia_telemetry/logging/__init__.py
pharia_telemetry/logging/injectors.py
pharia_telemetry/logging/processor.py
pharia_telemetry/sem_conv/__init__.py
pharia_telemetry/sem_conv/baggage.py
pharia_telemetry/sem_conv/gen_ai.py
pharia_telemetry/setup/__init__.py
pharia_telemetry/setup/setup.py
pharia_telemetry-0.1.1.dist-info/METADATA
pharia_telemetry-0.1.1.dist-info/WHEEL
pharia_telemetry-0.1.1.dist-info/licenses/LICENSE
pharia_telemetry-0.1.1.dist-info/RECORD
