Metadata-Version: 2.4
Name: pharia-telemetry
Version: 0.1.1
Summary: Telemetry utilities and shared components for Pharia projects
Project-URL: Homepage, https://github.com/aleph-alpha/pharia-telemetry
Project-URL: Documentation, https://pharia-telemetry.readthedocs.io
Project-URL: Repository, https://github.com/aleph-alpha/pharia-telemetry
Project-URL: Issues, https://github.com/aleph-alpha/pharia-telemetry/issues
Project-URL: Changelog, https://github.com/aleph-alpha/pharia-telemetry/blob/main/CHANGELOG.md
Author-email: Aleph Alpha Engineering <engineering@aleph-alpha.com>
License-Expression: MIT
License-File: LICENSE
Keywords: logging,metrics,observability,opentelemetry,telemetry,tracing
Classifier: Development Status :: 4 - Beta
Classifier: Intended Audience :: Developers
Classifier: License :: OSI Approved :: MIT License
Classifier: Operating System :: OS Independent
Classifier: Programming Language :: Python :: 3
Classifier: Programming Language :: Python :: 3.10
Classifier: Programming Language :: Python :: 3.11
Classifier: Programming Language :: Python :: 3.12
Classifier: Programming Language :: Python :: 3.13
Classifier: Topic :: Software Development :: Libraries :: Python Modules
Classifier: Topic :: System :: Logging
Classifier: Topic :: System :: Monitoring
Requires-Python: >=3.10
Requires-Dist: opentelemetry-api>=1.29.0
Requires-Dist: opentelemetry-sdk>=1.29.0
Requires-Dist: pydantic>=2.0.0
